bekeshbiron/__init__.py
bekeshbiron/_version.py
bekeshbiron-0.0.1.dist-info/AUTHORS.rst
bekeshbiron-0.0.1.dist-info/LICENSE
bekeshbiron-0.0.1.dist-info/METADATA
bekeshbiron-0.0.1.dist-info/WHEEL
bekeshbiron-0.0.1.dist-info/top_level.txt
bekeshbiron-0.0.1.dist-info/RECORD
