Metadata-Version: 2.1
Name: bekeshbiron
Version: 0.0.1
Summary: A VERY useful package that suppresses warnings!
Home-page: https://https://github.com/Salehbigdeli/bekeshbiron/Salehbigdeli/bekeshbiron
Author: Ali Akbar Saleh
Author-email: al.ak.saleh@gmail.com
License: LGPL-3.0-or-later
Project-URL: Changelog, https://https://github.com/Salehbigdeli/bekeshbiron/Salehbigdeli/bekeshbiron/blob/master/CHANGELOG.rst
Project-URL: Issue Tracker, https://https://github.com/Salehbigdeli/bekeshbiron/Salehbigdeli/bekeshbiron/issues
Platform: UNKNOWN
Classifier: Development Status :: 5 - Production/Stable
Classifier: Intended Audience :: Developers
Classifier: License :: OSI Approved :: GNU General Public License v3 (GPLv3)
Classifier: Operating System :: Unix
Classifier: Operating System :: POSIX
Classifier: Operating System :: Microsoft :: Windows
Classifier: Programming Language :: Python
Classifier: Programming Language :: Python :: 2.7
Classifier: Programming Language :: Python :: 3
Classifier: Programming Language :: Python :: 3.5
Classifier: Programming Language :: Python :: 3.6
Classifier: Programming Language :: Python :: 3.7
Classifier: Programming Language :: Python :: 3.8
Classifier: Programming Language :: Python :: Implementation :: CPython
Classifier: Programming Language :: Python :: Implementation :: PyPy
Classifier: Topic :: Utilities
Requires-Python: >=2.7, !=3.0.*, !=3.1.*, !=3.2.*, !=3.3.*, !=3.4.*
